ssh_channel/__init__.py
ssh_channel/main.py
ssh_channel/receive.py
ssh_channel/send.py
ssh_channel-1.0.0.dist-info/METADATA
ssh_channel-1.0.0.dist-info/WHEEL
ssh_channel-1.0.0.dist-info/entry_points.txt
ssh_channel-1.0.0.dist-info/top_level.txt
ssh_channel-1.0.0.dist-info/RECORD
